pyrate.py
pyrate_build-0.2.10.dist-info/DESCRIPTION.rst
pyrate_build-0.2.10.dist-info/METADATA
pyrate_build-0.2.10.dist-info/RECORD
pyrate_build-0.2.10.dist-info/WHEEL
pyrate_build-0.2.10.dist-info/entry_points.txt
pyrate_build-0.2.10.dist-info/metadata.json
pyrate_build-0.2.10.dist-info/top_level.txt
