Metadata-Version: 2.0
Name: pyrate-build
Version: 0.2.10
Summary: A small python based build file generator targeting ninja
Home-page: https://github.com/pyrate-build/pyrate-build
Author: Fred Stober
Author-email: fred.stober@gmx.de
License: License :: OSI Approved :: Apache Software License
Download-URL: https://github.com/pyrate-build/pyrate-build/tarball/0.2.10
Keywords: ninja build development
Platform: Operating System :: OS Independent
Classifier: Development Status :: 4 - Beta
Classifier: Intended Audience :: Developers
Classifier: Topic :: Software Development :: Build Tools
Classifier: License :: OSI Approved :: Apache Software License
Classifier: Operating System :: OS Independent
Classifier: Programming Language :: Python :: 2
Classifier: Programming Language :: Python :: 2.6
Classifier: Programming Language :: Python :: 2.7
Classifier: Programming Language :: Python :: 3
Classifier: Programming Language :: Python :: 3.2
Classifier: Programming Language :: Python :: 3.3
Classifier: Programming Language :: Python :: 3.4
Classifier: Programming Language :: Python :: 3.5
